README
setup.py
src/django_uuid/__init__.py
src/django_uuid/fields.py
src/django_uuid.egg-info/PKG-INFO
src/django_uuid.egg-info/SOURCES.txt
src/django_uuid.egg-info/dependency_links.txt
src/django_uuid.egg-info/requires.txt
src/django_uuid.egg-info/top_level.txt