Metadata-Version: 1.0
Name: django-uuid
Version: 0.1
Summary: UUID field for django
Home-page: https://github.com/gugu/django-uuid
Author: Andrii Kostenko
Author-email: andrey@kostenko.name
License: UNKNOWN
Platform: UNKNOWN
